[1,["15QsF1pnJBf4/O+uXJDFNv@f9941","7dj5uJT9FMn6OrOOx83tfK@f9941","1dpuJfkvpF5rfXlpUMuf28@f9941","d91tcUDzJIg7N69m3Eotuf@f9941","203ukU+1lGDbF0nYuvjkZg@f9941","5dStnHgQRJELcgwMm7gbL8@f9941","85KWq7C6pMuIU4iWwiXYff@f9941","15QsF1pnJBf4/O+uXJDFNv@6c48a","1dpuJfkvpF5rfXlpUMuf28@6c48a","203ukU+1lGDbF0nYuvjkZg@6c48a","5dStnHgQRJELcgwMm7gbL8@6c48a","7dj5uJT9FMn6OrOOx83tfK@6c48a","d91tcUDzJIg7N69m3Eotuf@6c48a"],["node","_spriteFrame","_textureSource","root","StoryBoard","Dialog","Click","handShadow","hand","mask","data","_parent"],[["cc.Node",["_name","_layer","_active","_components","_prefab","_parent","_children","_lpos","_lscale"],0,9,4,1,2,5,5],"cc.SpriteFrame",["cc.Sprite",["_sizeMode","_type","node","__prefab","_spriteFrame","_color"],1,1,4,6,5],["cc.Widget",["_alignFlags","_alignMode","_originalWidth","_originalHeight","_top","_bottom","node","__prefab"],-3,1,4],["cc.UITransform",["node","__prefab","_contentSize","_anchorPoint"],3,1,4,5,5],["cc.Label",["_string","_actualFontSize","_fontSize","_lineHeight","_overflow","node","__prefab","_color"],-2,1,4,5],["cc.Prefab",["_name"],2],["cc.CompPrefabInfo",["fileId"],2],["a9e2de9zoRJ6rvhIVOOQurq",["node","__prefab","mask","hand","handShadow","Click","Dialog","StoryBoard"],3,1,4,1,1,1,1,1,1],["cc.PrefabInfo",["fileId","instance","targetOverrides","nestedPrefabInstanceRoots","root","asset"],-1,1,1],["cc.BlockInputEvents",["node","__prefab"],3,1,4],["cc.UIOpacity",["node","__prefab"],3,1,4],["cc.Mask",["_type","_inverted","node","__prefab"],1,1,4]],[[7,0,2],[9,0,1,2,3,4,5,5],[4,0,1,2,1],[4,0,1,2,3,1],[2,2,3,4,1],[11,0,1,1],[0,0,1,6,3,4,3],[0,0,2,1,5,6,3,4,4],[0,0,2,1,5,3,4,7,4],[0,0,1,5,3,4,3],[3,0,2,3,6,7,4],[2,0,2,3,5,4,2],[2,1,0,2,3,4,3],[6,0,2],[0,0,1,5,6,3,4,3],[0,0,2,1,5,3,4,4],[0,0,1,5,3,4,7,3],[0,0,1,5,3,4,7,8,3],[8,0,1,2,3,4,5,6,7,1],[3,0,1,6,7,3],[3,0,4,5,1,6,7,5],[2,2,3,5,4,1],[10,0,1,1],[12,0,1,2,3,3],[5,0,1,2,3,4,5,6,7,6],[5,0,1,2,3,5,6,5]],[[[[13,"GuideLayer"],[6,"GuideLayer",33554432,[-11,-12,-13,-14,-15,-16],[[2,-2,[0,"02ah6MF85E5rZWrap/bARS"],[5,1080,1920]],[18,-9,[0,"04ddpYYNpK9IhCOHiKeeBA"],-8,-7,-6,-5,-4,-3],[10,45,100,100,-10,[0,"14ISy413JClp8WlAlPpoX3"]]],[1,"00Yhgda4NOuJ7o3FGcdaQo",null,null,null,-1,0]],[7,"StoryBoard",false,33554432,1,[-22],[[2,-17,[0,"eemPnpFeVBe6snyj6Ez//z"],[5,1080,1920]],[11,0,-18,[0,"2awSDjha1LrZyC/CjPhv7P"],[4,3525649712],7],[10,45,2,2,-19,[0,"a9nMJOab5E8pe5HcxwAYq4"]],[22,-20,[0,"ecS0/ybNpD0o3jGYcZ/hQV"]],[5,-21,[0,"49FTzfOD5I2o0yx8nkPX/4"]]],[1,"d6M07Kwv5CMLKLbJOVSwDR",null,null,null,1,0]],[14,"Mask",33554432,1,[-26],[[2,-23,[0,"ccu1slvbxK0Kuyu3XHsUz/"],[5,0,0]],[23,3,true,-24,[0,"26x8Kwg7hJuJHU+2bZfqnl"]],[12,1,0,-25,[0,"8cCWWX7f5Ov6UKSWEuB9gW"],1]],[1,"95QZod16REF6gS2/lFRElR",null,null,null,1,0]],[8,"HandShadow",false,33554432,1,[[3,-27,[0,"01VqLjTBBL6Idev3E9lVO2"],[5,290,260],[0,0.1,0.88]],[21,-28,[0,"9crFY5BxhPjoiMbfg2xREE"],[4,2852126720],2],[5,-29,[0,"46+nVGwmlBtbAad+gsS94D"]]],[1,"a2i1wVTc9Prozb0XzbZvfE",null,null,null,1,0],[1,0,-51.647,0]],[15,"Click",false,33554432,1,[[2,-30,[0,"07c2gzWpJO24gvAfqiW+eE"],[5,139,139]],[4,-31,[0,"d1a50wL9pL1YDPRkAykwZ3"],3],[5,-32,[0,"26xcpU/x5Cw4IdhvB0xNxb"]]],[1,"d8j8Kp7exFpJSkDeSmex6a",null,null,null,1,0]],[6,"bg",33554432,[-35,-36],[[3,-33,[0,"e2z7urC9FO0bOEdgN3JgSy"],[5,642,275],[0,0.5,0]],[12,1,0,-34,[0,"770/kaJRhFYoVaVvstIiX3"],6]],[1,"f52gIMvlpCToAZwqVQbCPG",null,null,null,1,0]],[8,"Hand",false,33554432,1,[[3,-37,[0,"bb17vUHNNE9bp2tK+jJxjy"],[5,290,260],[0,0.1,0.88]],[4,-38,[0,"1cflGUnT5EZLdt10hXncER"],4]],[1,"92+M4nfDpF+6/arcmwmtB7",null,null,null,1,0],[1,-77.813,129.688,0]],[7,"Dialog",false,33554432,1,[6],[[2,-39,[0,"f5fkQIp7VAR5toIFPuUbpJ"],[5,0,0]]],[1,"e7f7ELOE5DK5glXr8U2+NQ",null,null,null,1,0]],[16,"Label",33554432,6,[[2,-40,[0,"24q/e9HVNFnbK8S3BrIA53"],[5,500,69.3]],[24,"指针",48,48,55,3,-41,[0,"89WUYqL21LVJj82Q7qOi7d"],[4,4290414416]],[19,2,1,-42,[0,"99m3lmM+dFGaOmPHmBhNbD"]]],[1,"32c+YmPZRFzJK1lq16l00g",null,null,null,1,0],[1,0,137.5,0]],[17,"UI_UICommon_Arrow",33554432,6,[[2,-43,[0,"f3vj58MLxEC67Pd9zeUoCA"],[5,97,71]],[4,-44,[0,"8bG21RmTpOE4csjWUDFVPL"],5],[20,4,102,-23.299000000000007,1,-45,[0,"c76i86VVFJ6KzBgv1kVGxG"]]],[1,"540Qfh/jVGjZ8RZtlXOek0",null,null,null,1,0],[1,0,1.5509999999999913,0],[1,0.7,0.7,0.7]],[9,"blackBg",33554432,3,[[2,-46,[0,"e4K/Hrc79A+KEkDIfRSRyB"],[5,6000,6000]],[11,0,-47,[0,"7c07YtX6NC1IE0T3nP2fLX"],[4,3019898880],0]],[1,"6dLmw4DLhEybnSYj8ludpJ",null,null,null,1,0]],[9,"Label",33554432,2,[[2,-48,[0,"00lagikYVGCZ5WVlpCeIf7"],[5,825,69.3]],[25,"您被击败，您的军队被敌军打散！",55,55,55,-49,[0,"fdUKkyxppPcbtK0wnIfRd4"]]],[1,"3a5p9HUIxOAZ6VW3Kn5QGK",null,null,null,1,0]]],0,[0,3,1,0,0,1,0,4,2,0,5,8,0,6,5,0,7,4,0,8,7,0,9,3,0,0,1,0,0,1,0,-1,3,0,-2,4,0,-3,5,0,-4,7,0,-5,8,0,-6,2,0,0,2,0,0,2,0,0,2,0,0,2,0,0,2,0,-1,12,0,0,3,0,0,3,0,0,3,0,-1,11,0,0,4,0,0,4,0,0,4,0,0,5,0,0,5,0,0,5,0,0,6,0,0,6,0,-1,9,0,-2,10,0,0,7,0,0,7,0,0,8,0,0,9,0,0,9,0,0,9,0,0,10,0,0,10,0,0,10,0,0,11,0,0,11,0,0,12,0,0,12,0,10,1,6,11,8,49],[0,0,0,0,0,0,0,0],[1,1,1,1,1,1,1,1],[1,2,0,3,0,4,5,6]],[[{"name":"UI_UIBeginnerTutorial_Hand","rect":{"x":0,"y":0,"width":290,"height":260},"offset":{"x":0,"y":0},"originalSize":{"width":290,"height":260},"rotated":false,"capInsets":[0,0,0,0],"vertices":{"rawPosition":[-145,-130,0,145,-130,0,-145,130,0,145,130,0],"indexes":[0,1,2,2,1,3],"uv":[0,260,290,260,0,0,290,0],"nuv":[0,0,1,0,0,1,1,1],"minPos":{"x":-145,"y":-130,"z":0},"maxPos":{"x":145,"y":130,"z":0}},"packable":true,"pixelsToUnit":100,"pivot":{"x":0.5,"y":0.5},"meshType":0}],[1],0,[0],[2],[7]],[[{"name":"guideBack","rect":{"x":0,"y":0,"width":210,"height":210},"offset":{"x":0,"y":0},"originalSize":{"width":210,"height":210},"rotated":false,"capInsets":[30,44,33,26],"vertices":{"rawPosition":[-105,-105,0,105,-105,0,-105,105,0,105,105,0],"indexes":[0,1,2,2,1,3],"uv":[0,210,210,210,0,0,210,0],"nuv":[0,0,1,0,0,1,1,1],"minPos":{"x":-105,"y":-105,"z":0},"maxPos":{"x":105,"y":105,"z":0}},"packable":true,"pixelsToUnit":100,"pivot":{"x":0.5,"y":0.5},"meshType":0}],[1],0,[0],[2],[8]],[[{"name":"UI_UICommon_Arrow","rect":{"x":0,"y":0,"width":97,"height":71},"offset":{"x":0,"y":0},"originalSize":{"width":97,"height":71},"rotated":false,"capInsets":[0,0,0,0],"vertices":{"rawPosition":[-48.5,-35.5,0,48.5,-35.5,0,-48.5,35.5,0,48.5,35.5,0],"indexes":[0,1,2,2,1,3],"uv":[0,71,97,71,0,0,97,0],"nuv":[0,0,1,0,0,1,1,1],"minPos":{"x":-48.5,"y":-35.5,"z":0},"maxPos":{"x":48.5,"y":35.5,"z":0}},"packable":true,"pixelsToUnit":100,"pivot":{"x":0.5,"y":0.5},"meshType":0}],[1],0,[0],[2],[9]],[[{"name":"UI_UICommon_Board_11","rect":{"x":0,"y":0,"width":275,"height":275},"offset":{"x":0,"y":0},"originalSize":{"width":275,"height":275},"rotated":false,"capInsets":[62,55,62,77],"vertices":{"rawPosition":[-137.5,-137.5,0,137.5,-137.5,0,-137.5,137.5,0,137.5,137.5,0],"indexes":[0,1,2,2,1,3],"uv":[0,275,275,275,0,0,275,0],"nuv":[0,0,1,0,0,1,1,1],"minPos":{"x":-137.5,"y":-137.5,"z":0},"maxPos":{"x":137.5,"y":137.5,"z":0}},"packable":true,"pixelsToUnit":100,"pivot":{"x":0.5,"y":0.5},"meshType":0}],[1],0,[0],[2],[10]],[[{"name":"default_sprite_splash","rect":{"x":0,"y":0,"width":2,"height":2},"offset":{"x":0,"y":0},"originalSize":{"width":2,"height":2},"rotated":false,"capInsets":[0,0,0,0],"vertices":{"rawPosition":[-1,-1,0,1,-1,0,-1,1,0,1,1,0],"indexes":[0,1,2,2,1,3],"uv":[0,2,2,2,0,0,2,0],"nuv":[0,0,1,0,0,1,1,1],"minPos":{"x":-1,"y":-1,"z":0},"maxPos":{"x":1,"y":1,"z":0}},"packable":true,"pixelsToUnit":100,"pivot":{"x":0.5,"y":0.5},"meshType":0}],[1],0,[0],[2],[11]],[[{"name":"UI_UIBeginnerTutorial_Click","rect":{"x":0,"y":0,"width":139,"height":139},"offset":{"x":0,"y":0},"originalSize":{"width":139,"height":139},"rotated":false,"capInsets":[0,0,0,0],"vertices":{"rawPosition":[-69.5,-69.5,0,69.5,-69.5,0,-69.5,69.5,0,69.5,69.5,0],"indexes":[0,1,2,2,1,3],"uv":[0,139,139,139,0,0,139,0],"nuv":[0,0,1,0,0,1,1,1],"minPos":{"x":-69.5,"y":-69.5,"z":0},"maxPos":{"x":69.5,"y":69.5,"z":0}},"packable":true,"pixelsToUnit":100,"pivot":{"x":0.5,"y":0.5},"meshType":0}],[1],0,[0],[2],[12]]]]
