[1,["3bcZTTF9RGm7xmb0D9/+af","c3pZ9M9BxBzZlBC2u/1yzd@405f8","c3pZ9M9BxBzZlBC2u/1yzd@dc95d"],["node","_mesh","root","_parent","data"],[["cc.Node",["_name","_layer","_prefab","_parent","_children","_lpos","_components","_lrot","_euler"],1,4,1,2,5,9,5,5],["cc.Mesh",["_native","_hash","_struct"],1,11],["cc.Prefab",["_name"],2],["cc.Node",["_name","_layer","_parent","_children","_components","_prefab","_lrot","_euler"],1,1,9,9,4,5,5],["cc.PrefabInfo",["fileId","root","asset"],2,1,1],["cc.MeshRenderer",["node","__prefab","_materials","lightmapSettings","_mesh"],3,1,4,3,4,6],["cc.CompPrefabInfo",["fileId"],2],["cc.ModelLightmapSettings",[],3],["cc.UITransform",["node","__prefab","_contentSize"],3,1,4,5],["cc.UIMeshRenderer",["node","__prefab"],3,1,4]],[[6,0,2],[4,0,1,2,2],[1,0,1,2,3],[5,0,1,2,3,4,1],[7,1],[8,0,1,2,1],[9,0,1,1],[2,0,2],[0,0,1,4,2,3],[0,0,1,3,2,5,3],[0,0,1,3,6,2,7,8,3],[3,0,1,2,3,4,5,6,7,3]],[[[[2,".bin",2951156752,[{"primitives":[{"primitiveMode":7,"vertexBundelIndices":[0],"indexView":{"offset":31104,"length":6624,"count":1656,"stride":4}}],"vertexBundles":[{"view":{"offset":0,"length":31104,"count":648,"stride":48},"attributes":[{"name":"a_position","format":32,"isNormalized":false},{"name":"a_normal","format":32,"isNormalized":false},{"name":"a_texCoord","format":21,"isNormalized":false},{"name":"a_tangent","format":44,"isNormalized":false}]}]},"minPosition",8,[1,-0.1192345842719078,-1.0676543712615967,0.5344780087471008],"maxPosition",8,[1,0.1192345842719078,-0.4976276159286499,0.7747512459754944]]],-1],0,0,[],[],[]],[[[2,".bin",2495893366,[{"primitives":[{"primitiveMode":7,"vertexBundelIndices":[0],"indexView":{"offset":2688,"length":576,"count":144,"stride":4}}],"vertexBundles":[{"view":{"offset":0,"length":2688,"count":56,"stride":48},"attributes":[{"name":"a_position","format":32,"isNormalized":false},{"name":"a_normal","format":32,"isNormalized":false},{"name":"a_texCoord","format":21,"isNormalized":false},{"name":"a_tangent","format":44,"isNormalized":false}]}]},"minPosition",8,[1,-0.14419196546077728,-0.36873337626457214,0.5962694883346558],"maxPosition",8,[1,0.1441919356584549,-0.2021283656358719,0.9002617001533508]]],-1],0,0,[],[],[]],[[[7,"tank_player_barrel_3"],[8,"tank_player_barrel_3",8388608,[-2,-3],[1,"7auQdJEB1XV7qinBaZaMPz",-1,0]],[11,"tank_barrel",8388608,1,[[9,"Node",8388608,-7,[1,"2fo3L41LZK24JZVN5iF/pV",1,0],[1,0,-0.499,0.652]]],[[3,-4,[0,"45BSnqtMJafI0wxLNuFAht"],[0],[4],1],[5,-5,[0,"b1TwgiwtlHJLgmWna8C1i0"],[5,1,1]],[6,-6,[0,"ffaSUzY4RNsbG1nfAT1WPd"]]],[1,"41PhhddpBX7IAMntudqiDE",1,0],[3,-0.788010753606722,0,0,0.6156614753256583],[1,-104,0,0]],[10,"tank_barrel_base",8388608,1,[[3,-8,[0,"39comsMeVelrmU8XehcVvj"],[2],[4],3],[5,-9,[0,"d9nEPm31xOaKxJA5CMRHmz"],[5,1,1]],[6,-10,[0,"3eR7atZBBDW730+KX/lD7P"]]],[1,"2flkMynz1cKplfrw8/oRuB",1,0],[3,-0.7071067811865476,0,0,0.7071067811865476],[1,-90.00000000000003,0,0]]],0,[0,2,1,0,-1,2,0,-2,3,0,0,2,0,0,2,0,0,2,0,3,2,0,0,3,0,0,3,0,0,3,0,4,1,10],[0,0,0,0],[-1,1,-1,1],[0,1,0,2]]]]
